LICENSE
MANIFEST.in
pymodhook.py
setup.py
pymodhook-patches/_global.json
pymodhook-patches/json.json
pymodhook-patches/matplotlib.pyplot.json
pymodhook-patches/numpy.json
pymodhook-patches/pickle.json
pymodhook-patches/tkinter.json