Metadata-Version: 2.1
Name: pymodhook
Version: 1.0.2
Summary: A library for recording arbitrary calls to Python modules, primarily intended for Python reverse engineering and analysis.记录任意对Python模块的调用的库，主要用于Python逆向分析。
Home-page: https://github.com/qfcy/PyModuleHook
Author: qfcy
Author-email: 3076711200@qq.com
Keywords: python,module,hook,reverse,dynamic,逆向
Classifier: Programming Language :: Python
Classifier: Topic :: Software Development :: Debuggers
Classifier: Topic :: Software Development :: Bug Tracking
Classifier: Topic :: Software Development :: Object Brokering
Classifier: Topic :: Software Development :: Testing
License-File: LICENSE
